py_shell_runner-0.1.0.dev5.dist-info/licenses/LICENSE
pyshrun/__init__.py
pyshrun/__main__.py
pyshrun/helper.py
pyshrun/parser.py
pyshrun/run-example.yml
pyshrun/sh.py
pyshrun/types.py
py_shell_runner-0.1.0.dev5.dist-info/METADATA
py_shell_runner-0.1.0.dev5.dist-info/WHEEL
py_shell_runner-0.1.0.dev5.dist-info/entry_points.txt
py_shell_runner-0.1.0.dev5.dist-info/top_level.txt
py_shell_runner-0.1.0.dev5.dist-info/RECORD
