Metadata-Version: 2.4
Name: py-shell-runner
Version: 0.1.0.dev5
Summary: Python for shell scripting
Project-URL: repository, https://github.com/ThakeeNathees/pyshrun
Requires-Python: >=3.12
License-File: LICENSE
Requires-Dist: colorama>=0.4.6
Requires-Dist: pydantic>=2.11.7
Requires-Dist: pyyaml>=6.0.2
Dynamic: license-file
